aiocloudpayments/__init__.py
aiocloudpayments/client/__init__.py
aiocloudpayments/client/base.py
aiocloudpayments/client/client.py
aiocloudpayments/dispatcher/__init__.py
aiocloudpayments/dispatcher/aiohttp_dispatcher.py
aiocloudpayments/dispatcher/base_dispatcher.py
aiocloudpayments/dispatcher/callback.py
aiocloudpayments/dispatcher/handler.py
aiocloudpayments/dispatcher/notification_observer.py
aiocloudpayments/dispatcher/router.py
aiocloudpayments/dispatcher/typehints.py
aiocloudpayments/endpoints/__init__.py
aiocloudpayments/endpoints/applepay/__init__.py
aiocloudpayments/endpoints/applepay/startsession.py
aiocloudpayments/endpoints/base.py
aiocloudpayments/endpoints/notifications/__init__.py
aiocloudpayments/endpoints/notifications/get.py
aiocloudpayments/endpoints/notifications/update.py
aiocloudpayments/endpoints/orders/__init__.py
aiocloudpayments/endpoints/orders/cancel.py
aiocloudpayments/endpoints/orders/create.py
aiocloudpayments/endpoints/payments/__init__.py
aiocloudpayments/endpoints/payments/cards/__init__.py
aiocloudpayments/endpoints/payments/cards/auth.py
aiocloudpayments/endpoints/payments/cards/bases.py
aiocloudpayments/endpoints/payments/cards/charge.py
aiocloudpayments/endpoints/payments/cards/post3ds.py
aiocloudpayments/endpoints/payments/cards/topup.py
aiocloudpayments/endpoints/payments/confirm.py
aiocloudpayments/endpoints/payments/find.py
aiocloudpayments/endpoints/payments/find_v2.py
aiocloudpayments/endpoints/payments/get.py
aiocloudpayments/endpoints/payments/list.py
aiocloudpayments/endpoints/payments/refund.py
aiocloudpayments/endpoints/payments/tokens/__init__.py
aiocloudpayments/endpoints/payments/tokens/auth.py
aiocloudpayments/endpoints/payments/tokens/bases.py
aiocloudpayments/endpoints/payments/tokens/charge.py
aiocloudpayments/endpoints/payments/tokens/list.py
aiocloudpayments/endpoints/payments/tokens/topup.py
aiocloudpayments/endpoints/payments/void.py
aiocloudpayments/endpoints/subscriptions/__init__.py
aiocloudpayments-0.1.1.dist-info/LICENSE
aiocloudpayments-0.1.1.dist-info/WHEEL
aiocloudpayments-0.1.1.dist-info/METADATA
aiocloudpayments-0.1.1.dist-info/RECORD
