Metadata-Version: 2.1
Name: aiocloudpayments
Version: 0.1.1
Summary: CloudPayments Python Async Library
Home-page: https://github.com/drforse/aiocloudpayments
Keywords: cloudpayments,python,asyncio
Author: drforse
Author-email: george.lifeslice@gmail.com
Requires-Python: >=3.7,<4.0
Classifier: Programming Language :: Python :: 3
Classifier: Programming Language :: Python :: 3.7
Classifier: Programming Language :: Python :: 3.8
Classifier: Programming Language :: Python :: 3.9
Classifier: Programming Language :: Python :: 3.10
Classifier: Programming Language :: Python :: 3.11
Provides-Extra: ujson
Requires-Dist: aiohttp (>=3.8.1,<4.0.0)
Requires-Dist: pydantic (>=1.8.2,<2.0.0)
Project-URL: Repository, https://github.com/drforse/aiocloudpayments
